fonticon_mdi6/__init__.py
fonticon_mdi6/_iconfont.py
fonticon_mdi6/mdi6.py
fonticon_mdi6/fonts/LICENSE
fonticon_mdi6/fonts/materialdesignicons-webfont.ttf
fonticon_materialdesignicons6-6.9.96.dist-info/METADATA
fonticon_materialdesignicons6-6.9.96.dist-info/WHEEL
fonticon_materialdesignicons6-6.9.96.dist-info/entry_points.txt
fonticon_materialdesignicons6-6.9.96.dist-info/licenses/LICENSE
fonticon_materialdesignicons6-6.9.96.dist-info/RECORD
